LICENSE
README.md
typic/__init__.py
typic/api.py
typic/checks.py
typic/common.py
typic/compat.py
typic/constraints/__init__.py
typic/constraints/array.py
typic/constraints/common.py
typic/constraints/error.py
typic/constraints/factory.py
typic/constraints/mapping.py
typic/constraints/number.py
typic/constraints/text.py
typic/env.py
typic/ext/__init__.py
typic/ext/json.py
typic/ext/schema/__init__.py
typic/ext/schema/compat.py
typic/ext/schema/field.py
typic/ext/schema/schema.py
typic/gen.py
typic/klass.py
typic/mypy.py
typic/py.typed
typic/serde/__init__.py
typic/serde/binder.py
typic/serde/common.py
typic/serde/des.py
typic/serde/resolver.py
typic/serde/ser.py
typic/serde/translator.py
typic/strict.py
typic/types/__init__.py
typic/types/dsn.py
typic/types/email.py
typic/types/frozendict.py
typic/types/path.py
typic/types/secret.py
typic/types/url.py
typic/util.py
typical-2.9.0.dist-info/LICENSE
typical-2.9.0.dist-info/METADATA
typical-2.9.0.dist-info/WHEEL
typical-2.9.0.dist-info/RECORD
