Metadata-Version: 2.1
Name: typical
Version: 2.9.0
Summary: Typical: Python's Typing Toolkit.
Home-page: https://github.com/seandstewart/typical
License: MIT
Keywords: typing,data,annotations,validation,json-schema
Author: Sean Stewart
Author-email: sean_stewart@me.com
Requires-Python: >=3.8.1,<4.0
Classifier: Development Status :: 5 - Production/Stable
Classifier: Intended Audience :: Developers
Classifier: License :: OSI Approved :: MIT License
Classifier: Natural Language :: English
Classifier: Operating System :: OS Independent
Classifier: Programming Language :: Python
Classifier: Programming Language :: Python :: 3
Classifier: Programming Language :: Python :: 3.9
Classifier: Programming Language :: Python :: 3.10
Classifier: Programming Language :: Python :: 3.11
Classifier: Programming Language :: Python :: 3.12
Classifier: Programming Language :: Python :: 3 :: Only
Classifier: Programming Language :: Python :: 3.7
Classifier: Programming Language :: Python :: 3.8
Classifier: Programming Language :: Python :: Implementation :: CPython
Classifier: Topic :: Utilities
Classifier: Typing :: Typed
Provides-Extra: benchmarks
Provides-Extra: docs
Provides-Extra: json
Provides-Extra: lint
Provides-Extra: schema
Provides-Extra: tests
Requires-Dist: black (>=24,<25) ; extra == "lint"
Requires-Dist: django (>=4,<5) ; extra == "benchmarks"
Requires-Dist: djangorestframework (>=3,<4) ; extra == "benchmarks"
Requires-Dist: fastjsonschema (>=2,<3) ; extra == "schema" or extra == "tests"
Requires-Dist: flake8 (>=7,<8) ; extra == "lint"
Requires-Dist: future-typing (>=0.4.1,<0.5.0)
Requires-Dist: inflection (>=0.5,<0.6)
Requires-Dist: marshmallow (>=3,<4) ; extra == "benchmarks"
Requires-Dist: mkdocs (>=1,<2) ; extra == "docs"
Requires-Dist: mkdocs-awesome-pages-plugin (>=2,<3) ; extra == "docs"
Requires-Dist: mkdocs-material (>=9,<10) ; extra == "docs"
Requires-Dist: mypy (>=1,<2) ; extra == "tests" or extra == "lint"
Requires-Dist: orjson (>=3,<4) ; extra == "tests"
Requires-Dist: pandas (>=2.0,<3.0) ; (python_version >= "3.8" and python_version < "3.9") and (extra == "tests")
Requires-Dist: pandas (>=2.2,<3.0) ; (python_version >= "3.9" and python_version < "4.0") and (extra == "tests")
Requires-Dist: pendulum (>=3,<4)
Requires-Dist: pydantic[email] (>=1.0,<2.0) ; extra == "tests" or extra == "benchmarks" or extra == "benchmarks"
Requires-Dist: pymdown-extensions (>=10,<11) ; extra == "docs"
Requires-Dist: pytest (>=8,<9) ; extra == "tests"
Requires-Dist: pytest-benchmark[histogram] (>=4,<5) ; extra == "benchmarks"
Requires-Dist: pytest-cov (>=5,<6) ; extra == "tests"
Requires-Dist: sqlalchemy (>=2,<3) ; extra == "tests" or extra == "benchmarks"
Requires-Dist: toastedmarshmallow (>=2.15,<3.0) ; extra == "benchmarks"
Requires-Dist: types-python-dateutil ; extra == "lint"
Requires-Dist: types-setuptools ; extra == "lint"
Requires-Dist: types-toml ; extra == "lint"
Requires-Dist: types-typed-ast ; extra == "lint"
Requires-Dist: types-ujson ; extra == "lint"
Requires-Dist: typing-extensions (>=4,<5) ; python_version < "3.10"
Requires-Dist: ujson (>=5,<6) ; extra == "json" or extra == "tests"
Project-URL: Repository, https://github.com/seandstewart/typical
